Metadata-Version: 2.4
Name: definit-db
Version: 0.6.7
Summary: DefinIT database
Requires-Python: >=3.12
